fdsvismap/FDSVisMap.py
fdsvismap/Waypoint.py
fdsvismap/__init__.py
fdsvismap/helper_functions.py
fdsvismap-0.1.3.dist-info/METADATA
fdsvismap-0.1.3.dist-info/WHEEL
fdsvismap-0.1.3.dist-info/top_level.txt
fdsvismap-0.1.3.dist-info/RECORD
