Metadata-Version: 2.4
Name: fdsvismap
Version: 0.1.3
Summary: Tool for waypoint-based verification of visibility in the scope of performance-based fire safety assessment.
Author-email: Kristian Börger <boerger@uni-wuppertal.de>
License: MIT
Project-URL: Homepage, https://firedynamics.github.io/fdsvismap/
Project-URL: Repository, https://github.com/FireDynamics/fdsvismap
Project-URL: Bug Tracker, https://github.com/FireDynamics/fdsvismap/issues
Classifier: Programming Language :: Python :: 3
Classifier: License :: OSI Approved :: MIT License
Classifier: Operating System :: OS Independent
Requires-Dist: numpy~=1.26.4
Requires-Dist: matplotlib~=3.8.4
Requires-Dist: scikit-image~=0.23.2
Requires-Dist: fdsreader~=1.11.5
